data/amazon_reviews_en/README.md
data/amazon_reviews_en/amazon_reviews_multi-test.parquet
data/amazon_reviews_sp/README.md
data/amazon_reviews_sp/amazon_reviews_multi-test.parquet
data/api_examples/api_rest.json
docs/Makefile
docs/make.bat
docs/apidoc/conf.rst
docs/apidoc/modules.rst
docs/source/classes.rst
docs/source/conf.py
docs/source/definition.rst
docs/source/index.rst
docs/source/install.rst
docs/source/quickstart.rst
docs/source/notebooks/01_promptmeteo_usage.ipynb
docs/source/notebooks/02_model_tuning.ipynb
docs/source/notebooks/03_sentiment_analysis.ipynb
docs/source/notebooks/04_test_flant5_classification_prompts.ipynb
docs/source/notebooks/05_test_openai_classification_prompts.ipynb
docs/source/notebooks/06_test_openai_api-generation.ipynb
promptmeteo/__init__.py
promptmeteo/api_formatter.py
promptmeteo/api_generator.py
promptmeteo/base.py
promptmeteo/code_generator.py
promptmeteo/constants.py
promptmeteo/document_classifier.py
promptmeteo/document_qa.py
promptmeteo/summarizer.py
promptmeteo/tools.py
promptmeteo/validations.py
promptmeteo/models/__init__.py
promptmeteo/models/azure_openai.py
promptmeteo/models/base.py
promptmeteo/models/bedrock.py
promptmeteo/models/fake_llm.py
promptmeteo/models/google_vertexai.py
promptmeteo/models/hf_hub_api.py
promptmeteo/models/hf_pipeline.py
promptmeteo/models/openai.py
promptmeteo/parsers/__init__.py
promptmeteo/parsers/api_parser.py
promptmeteo/parsers/base.py
promptmeteo/parsers/classification_parser.py
promptmeteo/parsers/dummy_parser.py
promptmeteo/parsers/json_parser.py
promptmeteo/prompts/__init__.py
promptmeteo/prompts/anthropic.claude-v2_en_classification.prompt
promptmeteo/prompts/anthropic.claude-v2_en_summarization.prompt
promptmeteo/prompts/anthropic.claude-v2_es_classification.prompt
promptmeteo/prompts/anthropic.claude-v2_es_summarization.prompt
promptmeteo/prompts/base.py
promptmeteo/prompts/fake-static_en_api-correction.prompt
promptmeteo/prompts/fake-static_en_api-generation.prompt
promptmeteo-0.1.2.dist-info/LICENSE
promptmeteo-0.1.2.dist-info/METADATA
promptmeteo-0.1.2.dist-info/WHEEL
promptmeteo-0.1.2.dist-info/top_level.txt
promptmeteo-0.1.2.dist-info/RECORD
