Metadata-Version: 2.1
Name: promptmeteo
Version: 0.1.2
Summary: Enable the use of LLMs as a conventional ML model
Author-email: Angel Delgado <adelgado@paradigmadigital.com>
License: MIT License
Classifier: Development Status :: 4 - Beta
Classifier: License :: OSI Approved :: MIT License
Classifier: Programming Language :: Python :: 3
Classifier: Topic :: Software Development :: Libraries :: Python Modules
Classifier: Topic :: Scientific/Engineering :: Artificial Intelligence
Requires-Python: >=3.8
License-File: LICENSE
Requires-Dist: langchain ==0.0.351
Requires-Dist: pydantic ==1.10.11
Requires-Dist: faiss-cpu ==1.7.4
Requires-Dist: tiktoken ==0.4.0
Provides-Extra: all
Requires-Dist: promptmeteo[aws,dev,examples,google,huggingface,openai] ; extra == 'all'
Provides-Extra: aws
Requires-Dist: boto3 ==1.34.23 ; extra == 'aws'
Provides-Extra: dev
Requires-Dist: promptmeteo[test] ; extra == 'dev'
Requires-Dist: mkdocs ; extra == 'dev'
Requires-Dist: pre-commit ; extra == 'dev'
Requires-Dist: pip-tools ; extra == 'dev'
Requires-Dist: black ; extra == 'dev'
Requires-Dist: pylint ; extra == 'dev'
Requires-Dist: flake8 ; extra == 'dev'
Provides-Extra: docs
Requires-Dist: sphinx ==7.1.2 ; extra == 'docs'
Requires-Dist: furo ==2024.1.29 ; extra == 'docs'
Requires-Dist: numpydoc ==1.6.0 ; extra == 'docs'
Requires-Dist: sphinxcontrib-napoleon ==0.7 ; extra == 'docs'
Requires-Dist: pandoc ==2.3 ; extra == 'docs'
Requires-Dist: nbsphinx ==0.9.3 ; extra == 'docs'
Provides-Extra: examples
Requires-Dist: bumpver ; extra == 'examples'
Requires-Dist: jupyter ; extra == 'examples'
Requires-Dist: polars ; extra == 'examples'
Requires-Dist: seaborn ; extra == 'examples'
Requires-Dist: scikit-learn ; extra == 'examples'
Provides-Extra: google
Requires-Dist: google-cloud-aiplatform >=1.30.1 ; extra == 'google'
Provides-Extra: huggingface
Requires-Dist: torch ==2.0.1 ; extra == 'huggingface'
Requires-Dist: transformers ==4.31.0 ; extra == 'huggingface'
Requires-Dist: sentence-transformers ==2.2.2 ; extra == 'huggingface'
Provides-Extra: openai
Requires-Dist: openai ==0.27.8 ; extra == 'openai'
Provides-Extra: test
Requires-Dist: pytest ; extra == 'test'
Requires-Dist: coverage ; extra == 'test'
Requires-Dist: pytest-cov ; extra == 'test'
Requires-Dist: pytest-mock ; extra == 'test'
